setup.py
src/activecache.py
src/activecache.egg-info/PKG-INFO
src/activecache.egg-info/SOURCES.txt
src/activecache.egg-info/dependency_links.txt
src/activecache.egg-info/top_level.txt
src/tests/__init__.py
src/tests/test_cache.py