Metadata-Version: 1.1
Name: activecache
Version: 0.1.3
Summary: Active in-memory cache object for Python.
Home-page: git://github.com/Rethought/activecache
Author: ReThought Ltd
Author-email: code@rethought-solutions.com
License: BSD
Keywords: cache
Platform: UNKNOWN
Classifier: Intended Audience :: Developers
Classifier: License :: OSI Approved :: BSD License
Classifier: Operating System :: OS Independent
Classifier: Programming Language :: Python
